LICENSE
MANIFEST.in
README.md
setup.cfg
setup.py
pepfrag/__init__.py
pepfrag/constants.py
pepfrag/converters.cpp
pepfrag/converters.h
pepfrag/cpepfrag.cpp
pepfrag/cpepfrag.h
pepfrag/ion.h
pepfrag/iongenerator.cpp
pepfrag/iongenerator.h
pepfrag/mass.cpp
pepfrag/mass.h
pepfrag/pepfrag.py
pepfrag.egg-info/PKG-INFO
pepfrag.egg-info/SOURCES.txt
pepfrag.egg-info/dependency_links.txt
pepfrag.egg-info/top_level.txt