Metadata-Version: 2.1
Name: pepfrag
Version: 0.4.1
Summary: A library for peptide fragment ion generation
Home-page: https://github.com/ikcgroup/pepfrag
Author: Daniel Spencer
Author-email: danielspencer305@hotmail.co.uk
License: MIT
Keywords: PEPTIDE,MASS SPECTROMETRY,PROTEOMICS
Platform: UNKNOWN
Classifier: Development Status :: 4 - Beta
Classifier: Intended Audience :: Developers
Classifier: Topic :: Scientific/Engineering :: Bio-Informatics
Classifier: License :: OSI Approved :: MIT License
Classifier: Programming Language :: Python :: 3
Classifier: Programming Language :: Python :: 3.7
Classifier: Programming Language :: Python :: 3.8
